parq_blockmodel/__init__.py
parq_blockmodel/blockmodel.py
parq_blockmodel/geometry.py
parq_blockmodel/reblocking/__init__.py
parq_blockmodel/reblocking/conversion.py
parq_blockmodel/reblocking/downsample.py
parq_blockmodel/reblocking/reblocking.py
parq_blockmodel/reblocking/upsample.py
parq_blockmodel/types.py
parq_blockmodel/utils/__init__.py
parq_blockmodel/utils/cicd.py
parq_blockmodel/utils/demo_block_model.py
parq_blockmodel/utils/geometry_utils.py
parq_blockmodel/utils/pandas/__init__.py
parq_blockmodel/utils/pandas/aggregate.py
parq_blockmodel/utils/pandas_accessors.py
parq_blockmodel/utils/plotly_scraper.py
parq_blockmodel/utils/pyvista/__init__.py
parq_blockmodel/utils/pyvista/categorical_utils.py
parq_blockmodel/utils/pyvista/custom_plotter.py
parq_blockmodel/utils/pyvista/pyvista_utils.py
parq_blockmodel/utils/spatial_encoding.py
parq_blockmodel/utils/temporal/__init__.py
parq_blockmodel/utils/temporal/demo_data.py
parq_blockmodel/utils/temporal/temporal_surfaces.py
parq_blockmodel-0.1.8.dist-info/METADATA
parq_blockmodel-0.1.8.dist-info/WHEEL
parq_blockmodel-0.1.8.dist-info/licenses/LICENSE
parq_blockmodel-0.1.8.dist-info/RECORD
