Metadata-Version: 2.4
Name: parq-blockmodel
Version: 0.1.8
Summary: A Python package for efficient storage, manipulation, and analysis of mining block models using Parquet files.
License-File: LICENSE
Author: Greg
Author-email: 11791585+elphick@users.noreply.github.com
Requires-Python: >=3.11,<3.13
Classifier: Programming Language :: Python :: 3
Classifier: Programming Language :: Python :: 3.11
Classifier: Programming Language :: Python :: 3.12
Provides-Extra: all
Provides-Extra: profiling
Provides-Extra: progress
Provides-Extra: temporal
Provides-Extra: viz
Requires-Dist: geopandas (>=1.1.1,<2.0.0)
Requires-Dist: imageio (>=2.37.0,<3.0.0) ; extra == "temporal" or extra == "all"
Requires-Dist: imageio-ffmpeg (>=0.6.0,<0.7.0) ; extra == "temporal" or extra == "all"
Requires-Dist: kaleido (>=1.1.0,<2.0.0) ; extra == "viz"
Requires-Dist: numpy (>=1.25.2,<2.1)
Requires-Dist: parq-tools (>=0.3.1)
Requires-Dist: plotly (>=5.24.1) ; extra == "viz" or extra == "all"
Requires-Dist: pyarrow (>=16.0)
Requires-Dist: pyvista (>=0.44.2)
Requires-Dist: rioxarray (>=0.18.0) ; extra == "temporal" or extra == "all"
Requires-Dist: setuptools ; extra == "profiling" or extra == "all"
Requires-Dist: tqdm (>=4.67.1) ; extra == "progress" or extra == "all"
Requires-Dist: ydata-profiling (>=4.16.1) ; extra == "profiling" or extra == "all"
